json_configparser/__init__.py
json_configparser/bounds.py
json_configparser/config_args.py
json_configparser/type_defaults.py
json_configparser/validations.py
json_configparser-0.4.2.dist-info/LICENSE
json_configparser-0.4.2.dist-info/METADATA
json_configparser-0.4.2.dist-info/WHEEL
json_configparser-0.4.2.dist-info/top_level.txt
json_configparser-0.4.2.dist-info/RECORD
