Metadata-Version: 2.1
Name: json-configparser
Version: 0.4.2
Summary: A module that parses and validates JSON configuration files.
Home-page: https://github.com/GIlunga/JSON-Configparser
Author: Guilherme Ilunga
Author-email: guiilunga@hotmail.com
License: UNKNOWN
Project-URL: Bug Reports, https://github.com/GIlunga/JSON-Configparser/issues
Project-URL: Source, https://github.com/GIlunga/JSON-Configparser
Keywords: configuration options
Platform: UNKNOWN
Classifier: Development Status :: 3 - Alpha
Classifier: Intended Audience :: Developers
Classifier: License :: OSI Approved :: MIT License
Classifier: Programming Language :: Python :: 3.6
Classifier: Programming Language :: Python :: 3.7
Classifier: Programming Language :: Python :: 3.8
Requires-Python: >=3.6, <3.9
